{
  "date_blocked": null, 
  "citation": {
    "state_cite_three": null, 
    "federal_cite_one": "11 U.S. 434", 
    "federal_cite_two": null, 
    "specialty_cite_one": null, 
    "federal_cite_three": null, 
    "lexis_cite": "", 
    "document_uris": [
      "/api/rest/v2/document/85025/"
    ], 
    "scotus_early_cite": null, 
    "case_name": "Smith and Buchanan v. The Delaware Insurance Company", 
    "westlaw_cite": null, 
    "state_cite_one": null, 
    "neutral_cite": null, 
    "state_cite_regional": null, 
    "state_cite_two": null, 
    "docket_number": null, 
    "id": 52184, 
    "resource_uri": "/api/rest/v2/citation/52184/"
  }, 
  "id": 85025, 
  "blocked": false, 
  "judges": "", 
  "court": "/api/rest/v2/jurisdiction/scotus/", 
  "date_filed": "1813-03-18", 
  "download_url": "http://bulk.resource.org/courts.gov/c/US/11/11.US.434.html", 
  "source": "R", 
  "local_path": null, 
  "html_lawbox": "", 
  "time_retrieved": "2010-04-28T08:59:33", 
  "nature_of_suit": "", 
  "plain_text": "", 
  "html_with_citations": "<p class=\"case_cite\"><span class=\"citation no-link\"><span class=\"volume\">11</span> <span class=\"reporter\">U.S.</span> <span class=\"page\">434</span></span></p>\n    <p class=\"case_cite\">7 Cranch 434</p>\n    <p class=\"case_cite\">3 L.Ed. 396</p>\n    <p class=\"parties\">SMITH AND BUCHANAN<br>v.<br>THE DELAWARE INSURANCE COMPANY.</p>\n    <p class=\"date\">March 9, 1813</p>\n    <div class=\"num\" id=\"p1\">\n      <span class=\"num\">1</span>\n      <p class=\"indent\"><i>Absent</i>. WASHINGTON, <i>J. and</i> TODD, <i>J.</i></p>\n    </div>\n    <div class=\"num\" id=\"p2\">\n      <span class=\"num\">2</span>\n      <p class=\"indent\">ERROR to the Circuit Court for the district of Maryland, in an action of covenant on a policy of insurance.</p>\n    </div>\n    <div class=\"num\" id=\"p3\">\n      <span class=\"num\">3</span>\n      <p class=\"indent\">The jury found a verdict '<i>for the Defendants, subject to the opinion of the Court on the points reserved</i>.' And judgment was thereupon rendered '<i>for the Defendants accordingly</i>.'</p>\n    </div>\n    <div class=\"num\" id=\"p4\">\n      <span class=\"num\">4</span>\n      <p class=\"indent\">The Plaintiffs, by their counsel, moved the Court below that the points reserved (which the motion states, without stating the facts out of which they arose) and the opinion of the Court upon those points, should be entered on the record.</p>\n    </div>\n    <div class=\"num\" id=\"p5\">\n      <span class=\"num\">5</span>\n      <p class=\"indent\">The Court did not act on this motion; and, of course, the points do not appear, so as to enable this Court to take notice of them.</p>\n    </div>\n    <div class=\"num\" id=\"p6\">\n      <span class=\"num\">6</span>\n      <p class=\"indent\">The Defendants (it was said) would not agree to any arrangement by which the legal merits of the cause, as they appeared below, might come into discussion here.</p>\n    </div>\n    <div class=\"num\" id=\"p7\">\n      <span class=\"num\">7</span>\n      <p class=\"indent\">PINKNEY, <i>Attorney General, for Plaintiffs in error</i>,</p>\n    </div>\n    <div class=\"num\" id=\"p8\">\n      <span class=\"num\">8</span>\n      <p class=\"indent\">Contended that the verdict was imperfect, contradictory and void; and did not warrant the judgment pronounced upon it, nor any other judgment. 23 <i>Vin.</i> 397, <i>pl.</i> 10. It is neither a general nor a special verdict.</p>\n    </div>\n    <div class=\"num\" id=\"p9\">\n      <span class=\"num\">9</span>\n      <p class=\"indent\">HARPER, <i>contra</i>,</p>\n    </div>\n    <div class=\"num\" id=\"p10\">\n      <span class=\"num\">10</span>\n      <p class=\"indent\">Admitted that it was in form an irregular proceeding, but he was instructed to insist on the judgment.</p>\n    </div>\n    <div class=\"num\" id=\"p11\">\n      <span class=\"num\">11</span>\n      <p class=\"indent\">It is a general verdict for the Defendants: and by consent of parties it was referred to the Court; and if they should be of opinion that the verdict should not stand, they were to award a <i>venire de novo</i>. It was the negligence of the Plaintiffs in not having the facts, or the points and consent, stated on the record.</p>\n    </div>\n    <div class=\"num\" id=\"p12\">\n      <span class=\"num\">12</span>\n      <p class=\"indent\">It is evident that what was done was by consent. The Plaintiffs do not appear to have wished to bring the case here; but were at the time contented to rely on the opinion of the Court below.</p>\n    </div>\n    <div class=\"num\" id=\"p13\">\n      <span class=\"num\">13</span>\n      <p class=\"indent\">MARSHALL, <i>Ch. J.</i></p>\n    </div>\n    <div class=\"num\" id=\"p14\">\n      <span class=\"num\">14</span>\n      <p class=\"indent\">The case is too plain for argument. The jury did not intend to find a general verdict; but to submit the points of law to the Court. If the law had been for the Plaintiffs the Court could only have awarded a <i>venire de novo</i>. The facts ought to have appeared, so that the judgment might have been either reversed or affirmed upon the merits.</p>\n    </div>\n    <div class=\"num\" id=\"p15\">\n      <span class=\"num\">15</span>\n      <p class=\"indent\"><i>Judgment reversed, and a new trial awarded</i>.</p>\n    </div>\n    ", 
  "sha1": "736f03fc60d2227c046fea9c63158b05f9699a67", 
  "date_modified": "2014-12-21T01:23:49.471753", 
  "precedential_status": "Published", 
  "absolute_url": "/opinion/85025/smith-and-buchanan-v-the-delaware-insurance/", 
  "citation_count": 0, 
  "supreme_court_db_id": null, 
  "extracted_by_ocr": false, 
  "docket": "/api/rest/v2/docket/2157742/", 
  "html": "<p class=\"case_cite\">11 U.S. 434</p>\n    <p class=\"case_cite\">7 Cranch 434</p>\n    <p class=\"case_cite\">3 L.Ed. 396</p>\n    <p class=\"parties\">SMITH AND BUCHANAN<br>v.<br>THE DELAWARE INSURANCE COMPANY.</p>\n    <p class=\"date\">March 9, 1813</p>\n    <div class=\"num\" id=\"p1\">\n      <span class=\"num\">1</span>\n      <p class=\"indent\"><i>Absent</i>. WASHINGTON, <i>J. and</i> TODD, <i>J.</i></p>\n    </div>\n    <div class=\"num\" id=\"p2\">\n      <span class=\"num\">2</span>\n      <p class=\"indent\">ERROR to the Circuit Court for the district of Maryland, in an action of covenant on a policy of insurance.</p>\n    </div>\n    <div class=\"num\" id=\"p3\">\n      <span class=\"num\">3</span>\n      <p class=\"indent\">The jury found a verdict '<i>for the Defendants, subject to the opinion of the Court on the points reserved</i>.' And judgment was thereupon rendered '<i>for the Defendants accordingly</i>.'</p>\n    </div>\n    <div class=\"num\" id=\"p4\">\n      <span class=\"num\">4</span>\n      <p class=\"indent\">The Plaintiffs, by their counsel, moved the Court below that the points reserved (which the motion states, without stating the facts out of which they arose) and the opinion of the Court upon those points, should be entered on the record.</p>\n    </div>\n    <div class=\"num\" id=\"p5\">\n      <span class=\"num\">5</span>\n      <p class=\"indent\">The Court did not act on this motion; and, of course, the points do not appear, so as to enable this Court to take notice of them.</p>\n    </div>\n    <div class=\"num\" id=\"p6\">\n      <span class=\"num\">6</span>\n      <p class=\"indent\">The Defendants (it was said) would not agree to any arrangement by which the legal merits of the cause, as they appeared below, might come into discussion here.</p>\n    </div>\n    <div class=\"num\" id=\"p7\">\n      <span class=\"num\">7</span>\n      <p class=\"indent\">PINKNEY, <i>Attorney General, for Plaintiffs in error</i>,</p>\n    </div>\n    <div class=\"num\" id=\"p8\">\n      <span class=\"num\">8</span>\n      <p class=\"indent\">Contended that the verdict was imperfect, contradictory and void; and did not warrant the judgment pronounced upon it, nor any other judgment. 23 <i>Vin.</i> 397, <i>pl.</i> 10. It is neither a general nor a special verdict.</p>\n    </div>\n    <div class=\"num\" id=\"p9\">\n      <span class=\"num\">9</span>\n      <p class=\"indent\">HARPER, <i>contra</i>,</p>\n    </div>\n    <div class=\"num\" id=\"p10\">\n      <span class=\"num\">10</span>\n      <p class=\"indent\">Admitted that it was in form an irregular proceeding, but he was instructed to insist on the judgment.</p>\n    </div>\n    <div class=\"num\" id=\"p11\">\n      <span class=\"num\">11</span>\n      <p class=\"indent\">It is a general verdict for the Defendants: and by consent of parties it was referred to the Court; and if they should be of opinion that the verdict should not stand, they were to award a <i>venire de novo</i>. It was the negligence of the Plaintiffs in not having the facts, or the points and consent, stated on the record.</p>\n    </div>\n    <div class=\"num\" id=\"p12\">\n      <span class=\"num\">12</span>\n      <p class=\"indent\">It is evident that what was done was by consent. The Plaintiffs do not appear to have wished to bring the case here; but were at the time contented to rely on the opinion of the Court below.</p>\n    </div>\n    <div class=\"num\" id=\"p13\">\n      <span class=\"num\">13</span>\n      <p class=\"indent\">MARSHALL, <i>Ch. J.</i></p>\n    </div>\n    <div class=\"num\" id=\"p14\">\n      <span class=\"num\">14</span>\n      <p class=\"indent\">The case is too plain for argument. The jury did not intend to find a general verdict; but to submit the points of law to the Court. If the law had been for the Plaintiffs the Court could only have awarded a <i>venire de novo</i>. The facts ought to have appeared, so that the judgment might have been either reversed or affirmed upon the merits.</p>\n    </div>\n    <div class=\"num\" id=\"p15\">\n      <span class=\"num\">15</span>\n      <p class=\"indent\"><i>Judgment reversed, and a new trial awarded</i>.</p>\n    </div>\n    ", 
  "resource_uri": "/api/rest/v2/document/85025/"
}