{"absolute_url": "/opinion/1490379/rockwell-international-corp-v-united-states/", "blocked": false, "citation": {"case_name": "Rockwell International Corp. v. United States", "docket_number": "05-1272", "document_uris": ["/api/rest/v2/document/1490379/"], "federal_cite_one": "548 U.S. 941", "federal_cite_three": null, "federal_cite_two": null, "id": 1463150, "lexis_cite": null, "neutral_cite": null, "resource_uri": "/api/rest/v2/citation/1463150/", "scotus_early_cite": null, "specialty_cite_one": null, "state_cite_one": null, "state_cite_regional": null, "state_cite_three": null, "state_cite_two": null, "westlaw_cite": null}, "citation_count": 1, "court": "/api/rest/v2/jurisdiction/scotus/", "date_blocked": null, "date_filed": "2006-09-26", "date_modified": "2014-10-30T17:47:55.368428", "docket": "/api/rest/v2/docket/2575670/", "download_url": null, "extracted_by_ocr": false, "html": "", "html_lawbox": "<div>\n<center><b>548 U.S. 941 (2006)</b></center>\n<center><h1>ROCKWELL INTERNATIONAL CORP. ET AL.<br>\nv.<br>\nUNITED STATES ET AL.</h1></center>\n<center>No. 05-1272.</center>\n<center><p><b>Supreme Court of United States.</b></p></center>\n<center>September 26, 2006</center>\n<p>Certiorari granted limited to Question 1 presented by the petition. Petitioners' brief to be filed with the Clerk and served upon opposing counsel on or before 3 p.m., Thursday, October 26, 2006. Respondents' brief to be filed with the Clerk and served upon opposing counsel on or before 3 p.m., Monday, November 20, 2006. The reply brief, if any, to be filed with the Clerk and served upon opposing counsel on or before 3 p.m., Monday, November 27, 2006. JUSTICE BREYER took no part in the consideration or decision of this petition.</p>\n</div>", "html_with_citations": "<div>\n<center><b><span class=\"citation no-link\"><span class=\"volume\">548</span> <span class=\"reporter\">U.S.</span> <span class=\"page\">941</span></span> (2006)</b></center>\n<center><h1>ROCKWELL INTERNATIONAL CORP. ET AL.<br>\nv.<br>\nUNITED STATES ET AL.</h1></center>\n<center>No. 05-1272.</center>\n<center><p><b>Supreme Court of United States.</b></p></center>\n<center>September 26, 2006</center>\n<p>Certiorari granted limited to Question 1 presented by the petition. Petitioners' brief to be filed with the Clerk and served upon opposing counsel on or before 3 p.m., Thursday, October 26, 2006. Respondents' brief to be filed with the Clerk and served upon opposing counsel on or before 3 p.m., Monday, November 20, 2006. The reply brief, if any, to be filed with the Clerk and served upon opposing counsel on or before 3 p.m., Monday, November 27, 2006. JUSTICE BREYER took no part in the consideration or decision of this petition.</p>\n</div>", "id": 1490379, "judges": "", "local_path": null, "nature_of_suit": "", "plain_text": "", "precedential_status": "Published", "resource_uri": "/api/rest/v2/document/1490379/", "sha1": "9760df63b289fc75a15d3f660242d592fb837e86", "source": "L", "time_retrieved": "2013-10-29T23:28:01.057187"}